odoo/addons/storage_image_product/README.rst
odoo/addons/storage_image_product/__init__.py
odoo/addons/storage_image_product/__manifest__.py
odoo/addons/storage_image_product/i18n/storage_image_product.pot
odoo/addons/storage_image_product/models/__init__.py
odoo/addons/storage_image_product/models/category_image_relation.py
odoo/addons/storage_image_product/models/image_tag.py
odoo/addons/storage_image_product/models/product_category.py
odoo/addons/storage_image_product/models/product_image_relation.py
odoo/addons/storage_image_product/models/product_product.py
odoo/addons/storage_image_product/models/product_template.py
odoo/addons/storage_image_product/models/storage_image.py
odoo/addons/storage_image_product/readme/CONFIGURE.rst
odoo/addons/storage_image_product/readme/CONTRIBUTORS.rst
odoo/addons/storage_image_product/readme/DESCRIPTION.rst
odoo/addons/storage_image_product/readme/USAGE.rst
odoo/addons/storage_image_product/security/ir.model.access.csv
odoo/addons/storage_image_product/static/description/icon.png
odoo/addons/storage_image_product/static/description/index.html
odoo/addons/storage_image_product/tests/__init__.py
odoo/addons/storage_image_product/tests/common.py
odoo/addons/storage_image_product/tests/test_product_image_relation.py
odoo/addons/storage_image_product/tests/static/black-image.jpg
odoo/addons/storage_image_product/tests/static/logo-image.jpg
odoo/addons/storage_image_product/tests/static/white-image.jpg
odoo/addons/storage_image_product/views/image_tag.xml
odoo/addons/storage_image_product/views/product_category.xml
odoo/addons/storage_image_product/views/product_image_relation.xml
odoo/addons/storage_image_product/views/product_product.xml
odoo/addons/storage_image_product/views/product_template.xml
odoo/addons/storage_image_product/views/storage_image.xml
odoo12_addon_storage_image_product-12.0.1.2.2.dist-info/METADATA
odoo12_addon_storage_image_product-12.0.1.2.2.dist-info/WHEEL
odoo12_addon_storage_image_product-12.0.1.2.2.dist-info/top_level.txt
odoo12_addon_storage_image_product-12.0.1.2.2.dist-info/RECORD
